django_hadoop_storage-0.1.3.dist-info/DESCRIPTION.rst
django_hadoop_storage-0.1.3.dist-info/METADATA
django_hadoop_storage-0.1.3.dist-info/RECORD
django_hadoop_storage-0.1.3.dist-info/WHEEL
django_hadoop_storage-0.1.3.dist-info/metadata.json
django_hadoop_storage-0.1.3.dist-info/top_level.txt
hadoop_storage/__init__.py
