Metadata-Version: 2.0
Name: django-hadoop-storage
Version: 0.1.3
Summary: Module for use hadoop file system (hdfs) as django storage
Home-page: https://sofisis.com
Author: Cesar Augusto Cadavid Lopera
Author-email: cesar57927@gmail.com
License: BSD
Platform: UNKNOWN
Classifier: Programming Language :: Python :: 3.6
Classifier: Programming Language :: Python :: 3.7
Classifier: Programming Language :: Python :: 3.8
Classifier: Programming Language :: Python :: 3.9
Classifier: Framework :: Django :: 2.2
Classifier: Framework :: Django :: 3.0
Classifier: License :: OSI Approved :: BSD License
Classifier: Operating System :: POSIX :: Linux
Classifier: Operating System :: MacOS
Classifier: Topic :: System :: Filesystems
Classifier: Development Status :: 5 - Production/Stable
Classifier: Topic :: Software Development :: Libraries :: Python Modules
Requires-Python: >=3.6
Requires-Dist: django
Requires-Dist: pyarrow
Requires-Dist: Unidecode
